einnovationlabs/__init__.py
einnovationlabs/version.py
einnovationlabs_python_lib-0.0.1.1.dist-info/METADATA
einnovationlabs_python_lib-0.0.1.1.dist-info/WHEEL
einnovationlabs_python_lib-0.0.1.1.dist-info/top_level.txt
einnovationlabs_python_lib-0.0.1.1.dist-info/RECORD
