Metadata-Version: 2.1
Name: einnovationlabs-python-lib
Version: 0.0.1.1
Summary: A package for einnovationlabs' utility functions
Home-page: https://github.com/einnovationlabs/einnovationlabs-python-lib
Author: einnovationlabs Developer Team
Author-email: dev@einnovationlabs.com
Classifier: Programming Language :: Python :: 3
Classifier: License :: OSI Approved :: MIT License
Classifier: Operating System :: OS Independent
